sdkcpc/__init__.py
sdkcpc/__main__.py
sdkcpc/about.py
sdkcpc/build.py
sdkcpc/check.py
sdkcpc/common.py
sdkcpc/config.py
sdkcpc/info.py
sdkcpc/new.py
sdkcpc/run.py
sdkcpc/sdkcpc.yml
sdkcpc/resources/gitignore
sdkcpc/resources/idsk/darwin/iDSK
sdkcpc/resources/idsk/linux/iDSK
sdkcpc/resources/idsk/linux/x64/iDSK
sdkcpc/resources/idsk/win32/cyggcc_s-1.dll
sdkcpc/resources/idsk/win32/cygwin1.dll
sdkcpc/resources/idsk/win32/iDSK.exe
sdkcpc/resources/vscode/amstrad.json.code-snippets
sdkcpc/resources/vscode/tasks.json
tests/__init__.py
tests/test_sdkcpc.py
sdkcpc-0.0.1.dist-info/LICENSE
sdkcpc-0.0.1.dist-info/METADATA
sdkcpc-0.0.1.dist-info/WHEEL
sdkcpc-0.0.1.dist-info/entry_points.txt
sdkcpc-0.0.1.dist-info/top_level.txt
sdkcpc-0.0.1.dist-info/RECORD
